pylinlin/__init__.py
pylinlin/givens.py
pylinlin/householder.py
pylinlin/lu_factorization.py
pylinlin/matrix.py
pylinlin/matrix_utils.py
pylinlin/matrix_view.py
pylinlin/qr_factorization.py
pylinlin/svd.py
tests/__init__.py
tests/test_givens.py
tests/test_householder.py
tests/test_lu_factorization.py
tests/test_matrix.py
tests/test_matrix_utils.py
tests/test_qr_factorization.py
tests/test_svd.py
pylinlin-0.0.4.dist-info/LICENSE
pylinlin-0.0.4.dist-info/METADATA
pylinlin-0.0.4.dist-info/WHEEL
pylinlin-0.0.4.dist-info/top_level.txt
pylinlin-0.0.4.dist-info/RECORD
