Metadata-Version: 2.1
Name: pylinlin
Version: 0.0.4
Summary: A nice linear algebra library
Home-page: https://github.com/owenl131/pylinlin
Author: Owen Leong
Author-email: owenl131@gmail.com
License: UNKNOWN
Platform: UNKNOWN
Classifier: Programming Language :: Python :: 3
Classifier: License :: OSI Approved :: MIT License
Classifier: Operating System :: OS Independent
Requires-Python: >=3.8
